cloudedge/__init__.py
cloudedge/_version.py
cloudedge/cli.py
cloudedge/client.py
cloudedge/constants.py
cloudedge/exceptions.py
cloudedge/iot_parameters.py
cloudedge/logging_config.py
cloudedge/utils.py
cloudedge/validators.py
pycloudedge-0.1.3.dist-info/licenses/LICENSE
pycloudedge-0.1.3.dist-info/METADATA
pycloudedge-0.1.3.dist-info/WHEEL
pycloudedge-0.1.3.dist-info/entry_points.txt
pycloudedge-0.1.3.dist-info/top_level.txt
pycloudedge-0.1.3.dist-info/RECORD
