Metadata-Version: 2.4
Name: pycloudedge
Version: 0.1.3
Summary: Python library for CloudEdge cameras
Home-page: https://github.com/fradaloisio/pycloudedge
Author: Francesco D'Aloisio
Maintainer: Francesco D'Aloisio
License: Apache-2.0
Project-URL: Homepage, https://github.com/fradaloisio/pycloudedge
Project-URL: Bug Reports, https://github.com/fradaloisio/pycloudedge/issues
Project-URL: Source, https://github.com/fradaloisio/pycloudedge
Project-URL: Documentation, https://pycloudedge.readthedocs.io/
Keywords: cloudedge,smarteye,cameras,iot,api,home-automation,homeassistant
Classifier: Development Status :: 4 - Beta
Classifier: Intended Audience :: Developers
Classifier: Operating System :: OS Independent
Classifier: Programming Language :: Python :: 3
Classifier: Programming Language :: Python :: 3.7
Classifier: Programming Language :: Python :: 3.8
Classifier: Programming Language :: Python :: 3.9
Classifier: Programming Language :: Python :: 3.10
Classifier: Programming Language :: Python :: 3.11
Classifier: Programming Language :: Python :: 3.12
Classifier: Topic :: Home Automation
Classifier: Topic :: Internet :: WWW/HTTP :: Dynamic Content
Classifier: Topic :: Software Development :: Libraries :: Python Modules
Requires-Python: >=3.7
License-File: LICENSE
Requires-Dist: requests>=2.25.0
Requires-Dist: cryptography>=3.4.0
Requires-Dist: python-dotenv>=0.19.0
Provides-Extra: dev
Requires-Dist: pytest>=6.0; extra == "dev"
Requires-Dist: pytest-asyncio>=0.18.0; extra == "dev"
Requires-Dist: black>=21.0.0; extra == "dev"
Requires-Dist: flake8>=3.8.0; extra == "dev"
Requires-Dist: mypy>=0.910; extra == "dev"
Requires-Dist: twine>=3.4.0; extra == "dev"
Requires-Dist: build>=0.7.0; extra == "dev"
Provides-Extra: examples
Requires-Dist: python-dotenv>=0.19.0; extra == "examples"
Dynamic: home-page
Dynamic: license-file
Dynamic: requires-python
